Workbook

Sheet Dashboard
A1: 📊 SALES DASHBOARD — Farhana Akter Mim
A2: Excel & Data Analysis Project | 2024 Annual Report
B4: Total Revenue | D4: Total Orders | F4: Avg Order Value | H4: Total Profit
B5: =SUM(Sales!E2:E49) | D5: =COUNTA(Sales!A2:A49) | F5: =AVERAGE(Sales!E2:E49) | H5: =SUM(Sales!F2:F49)

Sheet Sales
A1: Order ID | B1: Month | C1: Product | D1: Category | E1: Revenue | F1: Profit | G1: Units | H1: Region | I1: Salesperson
A2: ORD-1001 | B2: Jan | C2: Phone | D2: Electronics | E2: 838.65 | F2: 221.63 | G2: 1 | H2: South | I2: Farhana
A3: ORD-1002 | B3: Feb | C3: Phone | D3: Electronics | E3: 6605.19 | F3: 2109.41 | G3: 9 | H3: North | I3: Alice
A4: ORD-1003 | B4: Mar | C4: Desk | D4: Furniture | E4: 1601.71 | F4: 411.82 | G4: 4 | H4: South | I4: Farhana
A5: ORD-1004 | B5: Apr | C5: Notebook | D5: Stationery | E5: 99.13 | F5: 35.94 | G5: 7 | H5: North | I5: Bob
A6: ORD-1005 | B6: May | C6: Keyboard | D6: Electronics | E6: 573.34 | F6: 164.63 | G6: 6 | H6: East | I6: Alice
A7: ORD-1006 | B7: Jun | C7: Phone | D7: Electronics | E7: 5148.32 | F7: 1855.14 | G7: 7 | H7: East | I7: Alice
A8: ORD-1007 | B8: Jul | C8: Mouse | D8: Electronics | E8: 499.48 | F8: 182.52 | G8: 9 | H8: North | I8: Emma
A9: ORD-1008 | B9: Aug | C9: Chair | D9: Furniture | E9: 2692.73 | F9: 718.87 | G9: 10 | H9: South | I9: Farhana
A10: ORD-1009 | B10: Sep | C10: Phone | D10: Electronics | E10: 825.8 | F10: 259.66 | G10: 1 | H10: North | I10: Bob
A11: ORD-1010 | B11: Oct | C11: Phone | D11: Electronics | E11: 5351.33 | F11: 1748.38 | G11: 7 | H11: East | I11: Bob
A12: ORD-1011 | B12: Nov | C12: Monitor | D12: Electronics | E12: 2543.13 | F12: 753.38 | G12: 6 | H12: North | I12: Emma
A13: ORD-1012 | B13: Dec | C13: Tablet | D13: Electronics | E13: 5647.46 | F13: 1456.41 | G13: 9 | H13: West | I13: Carlos
... A49: ORD-1048 | B49: Dec | C49: Monitor | D49: Electronics | E49: 811.68 | F49: 279.81 | G49: 2 | H49: North | I49: Alice

Sheet Monthly Summary
A1: Monthly Sales Summary
A2: Month | B2: Orders | C2: Revenue | D2: Profit | E2: Profit Margin
A3: Jan | B3: =COUNTIF(Sales!B:B,A3) | C3: =SUMIF(Sales!B:B,A3,Sales!E:E) | D3: =SUMIF(Sales!B:B,A3,Sales!F:F) | E3: =IF(C3=0,0,D3/C3)
A4: Feb | B4: =COUNTIF(Sales!B:B,A4) | C4: =SUMIF(Sales!B:B,A4,Sales!E:E) | D4: =SUMIF(Sales!B:B,A4,Sales!F:F) | E4: =IF(C4=0,0,D4/C4)
A5: Mar | B5: =COUNTIF(Sales!B:B,A5) | C5: =SUMIF(Sales!B:B,A5,Sales!E:E) | D5: =SUMIF(Sales!B:B,A5,Sales!F:F) | E5: =IF(C5=0,0,D5/C5)
A6: Apr | B6: =COUNTIF(Sales!B:B,A6) | C6: =SUMIF(Sales!B:B,A6,Sales!E:E) | D6: =SUMIF(Sales!B:B,A6,Sales!F:F) | E6: =IF(C6=0,0,D6/C6)
A7: May | B7: =COUNTIF(Sales!B:B,A7) | C7: =SUMIF(Sales!B:B,A7,Sales!E:E) | D7: =SUMIF(Sales!B:B,A7,Sales!F:F) | E7: =IF(C7=0,0,D7/C7)
A8: Jun | B8: =COUNTIF(Sales!B:B,A8) | C8: =SUMIF(Sales!B:B,A8,Sales!E:E) | D8: =SUMIF(Sales!B:B,A8,Sales!F:F) | E8: =IF(C8=0,0,D8/C8)
A9: Jul | B9: =COUNTIF(Sales!B:B,A9) | C9: =SUMIF(Sales!B:B,A9,Sales!E:E) | D9: =SUMIF(Sales!B:B,A9,Sales!F:F) | E9: =IF(C9=0,0,D9/C9)
A10: Aug | B10: =COUNTIF(Sales!B:B,A10) | C10: =SUMIF(Sales!B:B,A10,Sales!E:E) | D10: =SUMIF(Sales!B:B,A10,Sales!F:F) | E10: =IF(C10=0,0,D10/C10)
A11: Sep | B11: =COUNTIF(Sales!B:B,A11) | C11: =SUMIF(Sales!B:B,A11,Sales!E:E) | D11: =SUMIF(Sales!B:B,A11,Sales!F:F) | E11: =IF(C11=0,0,D11/C11)
A12: Oct | B12: =COUNTIF(Sales!B:B,A12) | C12: =SUMIF(Sales!B:B,A12,Sales!E:E) | D12: =SUMIF(Sales!B:B,A12,Sales!F:F) | E12: =IF(C12=0,0,D12/C12)
A13: Nov | B13: =COUNTIF(Sales!B:B,A13) | C13: =SUMIF(Sales!B:B,A13,Sales!E:E) | D13: =SUMIF(Sales!B:B,A13,Sales!F:F) | E13: =IF(C13=0,0,D13/C13)
A14: Dec | B14: =COUNTIF(Sales!B:B,A14) | C14: =SUMIF(Sales!B:B,A14,Sales!E:E) | D14: =SUMIF(Sales!B:B,A14,Sales!F:F) | E14: =IF(C14=0,0,D14/C14)
A15: TOTAL | B15: =SUM(B3:B14) | C15: =SUM(C3:C14) | D15: =SUM(D3:D14) | E15: =IF(C15=0,0,D15/C15)

Sheet Category Analysis
A1: Sales by Category
A2: Category | B2: Revenue | C2: Profit | D2: % of Total Revenue
A3: Electronics | B3: =SUMIF(Sales!D:D,A3,Sales!E:E) | C3: =SUMIF(Sales!D:D,A3,Sales!F:F) | D3: =IF(SUM(B3:B5)=0,0,B3/SUM(B3:B5))
A4: Furniture | B4: =SUMIF(Sales!D:D,A4,Sales!E:E) | C4: =SUMIF(Sales!D:D,A4,Sales!F:F) | D4: =IF(SUM(B3:B5)=0,0,B4/SUM(B3:B5))
A5: Stationery | B5: =SUMIF(Sales!D:D,A5,Sales!E:E) | C5: =SUMIF(Sales!D:D,A5,Sales!F:F) | D5: =IF(SUM(B3:B5)=0,0,B5/SUM(B3:B5))

Sheet Region Analysis
A1: Sales by Region
A2: Region | B2: Revenue | C2: Orders | D2: Avg Order Value
A3: North | B3: =SUMIF(Sales!H:H,A3,Sales!E:E) | C3: =COUNTIF(Sales!H:H,A3) | D3: =IF(C3=0,0,B3/C3)
A4: South | B4: =SUMIF(Sales!H:H,A4,Sales!E:E) | C4: =COUNTIF(Sales!H:H,A4) | D4: =IF(C4=0,0,B4/C4)
A5: East | B5: =SUMIF(Sales!H:H,A5,Sales!E:E) | C5: =COUNTIF(Sales!H:H,A5) | D5: =IF(C5=0,0,B5/C5)
A6: West | B6: =SUMIF(Sales!H:H,A6,Sales!E:E) | C6: =COUNTIF(Sales!H:H,A6) | D6: =IF(C6=0,0,B6/C6)
